build/lib/build/lib/pyutil_cfg/__init__.py
build/lib/build/lib/pyutil_cfg/cfg.py
build/lib/build/lib/pyutil_cfg/config_from_ini_file.py
build/lib/build/lib/pyutil_cfg/config_from_toml_file.py
build/lib/build/lib/pyutil_cfg/init_logger.py
build/lib/build/lib/pyutil_cfg/recursive_update.py
build/lib/build/lib/pyutil_cfg/types.py
build/lib/build/lib/pyutil_cfg/utils.py
build/lib/pyutil_cfg/__init__.py
build/lib/pyutil_cfg/cfg.py
build/lib/pyutil_cfg/config_from_ini_file.py
build/lib/pyutil_cfg/config_from_toml_file.py
build/lib/pyutil_cfg/init_logger.py
build/lib/pyutil_cfg/recursive_update.py
build/lib/pyutil_cfg/types.py
build/lib/pyutil_cfg/utils.py
pyutil_cfg/__init__.py
pyutil_cfg/cfg.py
pyutil_cfg/config_from_ini_file.py
pyutil_cfg/config_from_toml_file.py
pyutil_cfg/init_logger.py
pyutil_cfg/recursive_update.py
pyutil_cfg/types.py
pyutil_cfg/utils.py
pyutil_cfg-0.2.0.dist-info/licenses/LICENSE
pyutil_cfg-0.2.0.dist-info/METADATA
pyutil_cfg-0.2.0.dist-info/WHEEL
pyutil_cfg-0.2.0.dist-info/top_level.txt
pyutil_cfg-0.2.0.dist-info/RECORD
