Metadata-Version: 2.4
Name: pyutil-cfg
Version: 0.2.0
Summary: python util for cfg (configurations)
Author-email: Chuan-Heng Hsiao <hsiao.chuanheng@gmail.com>
License: Copyright 2025 Chuan-Heng Hsiao
Project-URL: Repository, https://github.com/chhsiao1981/pyutil-cfg
Classifier: Programming Language :: Python :: 3
Classifier: Programming Language :: Python :: 3.10
Classifier: Programming Language :: Python :: 3.11
Classifier: Programming Language :: Python :: 3.12
Classifier: Programming Language :: Python :: 3.13
Classifier: Programming Language :: Python :: 3.14
Classifier: License :: OSI Approved :: MIT License
Classifier: Operating System :: OS Independent
Requires-Python: >=3.10
License-File: LICENSE
Requires-Dist: tomli==2.2.1; python_version < "3.11"
Requires-Dist: typing-extensions==4.12.2; python_version < "3.11"
Dynamic: license-file
